Metadata-Version: 1.0
Name: willacy-cardGames
Version: 0.3
Summary: Card game Old Maid
Home-page: UNKNOWN
Author: Andrew Willacy
Author-email: UNKNOWN
License: UNKNOWN
Platform: UNKNOWN
